app_example/__init__.py
app_example/example.py
olivetti_test-0.0.1.dist-info/METADATA
olivetti_test-0.0.1.dist-info/WHEEL
olivetti_test-0.0.1.dist-info/top_level.txt
olivetti_test-0.0.1.dist-info/RECORD
